faster/__init__.py
faster/__main__.py
faster/const.py
faster/event.py
faster/filereader.py
faster/dataunpackers/__init__.py
faster/dataunpackers/type_0.py
faster/dataunpackers/type_10.py
faster/dataunpackers/type_61.py
faster/dataunpackers/type_62.py
faster/dataunpackers/type_70.py
faster/test/test_0001.fast
faster_filereader-1.0.0.dist-info/AUTHORS
faster_filereader-1.0.0.dist-info/LICENSE
faster_filereader-1.0.0.dist-info/METADATA
faster_filereader-1.0.0.dist-info/WHEEL
faster_filereader-1.0.0.dist-info/top_level.txt
faster_filereader-1.0.0.dist-info/RECORD
